image_grabber/__init__.py
image_grabber/image_grabber.py
image_grabber-1.0.2.data/scripts/image_grabber
image_grabber-1.0.2.dist-info/DESCRIPTION.rst
image_grabber-1.0.2.dist-info/METADATA
image_grabber-1.0.2.dist-info/metadata.json
image_grabber-1.0.2.dist-info/RECORD
image_grabber-1.0.2.dist-info/top_level.txt
image_grabber-1.0.2.dist-info/WHEEL
