Metadata-Version: 2.0
Name: image-grabber
Version: 1.0.2
Summary: Grab the first page of images from Bing Image search.
Home-page: https://github.com/jeffrand/image-grabber
Author: Jeff Rand
Author-email: jeffreyrand@gmail.com
License: UNKNOWN
Platform: UNKNOWN
Requires-Dist: appnope (==0.1.0)
Requires-Dist: decorator (==4.0.6)
Requires-Dist: gnureadline (==6.3.3)
Requires-Dist: image-grabber (==1.0.0)
Requires-Dist: ipdb (==0.8.1)
Requires-Dist: ipython-genutils (==0.1.0)
Requires-Dist: ipython (==4.1.1)
Requires-Dist: lxml (==3.5.0)
Requires-Dist: path.py (==8.1.2)
Requires-Dist: pexpect (==4.0.1)
Requires-Dist: pickleshare (==0.6)
Requires-Dist: ptyprocess (==0.5.1)
Requires-Dist: requests (==2.9.1)
Requires-Dist: simplegeneric (==0.8.1)
Requires-Dist: traitlets (==4.1.0)
Requires-Dist: wheel (==0.24.0)
